<?xml version="1.0"?>
<!DOCTYPE hibernate-mapping PUBLIC "-//Hibernate/Hibernate Mapping DTD 3.0//EN"
"http://www.hibernate.org/dtd/hibernate-mapping-3.0.dtd">
<!-- Generated 02-mar-2021 16:38:39 by Hibernate Tools 4.3.1 -->
<hibernate-mapping>
    <class name="models.Dept" table="DEPT" schema="SYSTEM">
        <id name="deptNo" type="int">
            <column name="DEPT_NO" precision="9" scale="0" />
            <generator class="assigned"></generator>
        </id>
        <property name="dnombre" type="string">
            <column name="DNOMBRE" length="50" />
        </property>
        <property name="loc" type="string">
            <column name="LOC" length="50" />
        </property>
    </class>
</hibernate-mapping>
